stapomog/__init__.py
stapomog/config.py
stapomog/generate.py
stapomog/templates.py
stapomog/utils.py
suvorov/__init__.py
suvorov/ck2file.py
suvorov/conf.py
suvorov/convert.py
suvorov/main.py
suvorov/service.py
suvorov/setup.py
suvorov/suvfile.py
vermeer/__init__.py
vermeer/__pkginfo__.py
vermeer/api.py
vermeer/library.py
stapomog-0.2.1.dist-info/LICENSE
stapomog-0.2.1.dist-info/METADATA
stapomog-0.2.1.dist-info/WHEEL
stapomog-0.2.1.dist-info/entry_points.txt
stapomog-0.2.1.dist-info/top_level.txt
stapomog-0.2.1.dist-info/RECORD
