Metadata-Version: 2.1
Name: stapomog
Version: 0.2.1
Summary: Tool to quickly create Static Portrait Mods for Crusader Kings 2
Home-page: https://github.com/krateng/stapomog
Author: Johannes Krattenmacher
Author-email: misc@krateng.dev
License: GPLv3
Platform: UNKNOWN
Classifier: Programming Language :: Python :: 3
Classifier: License :: OSI Approved :: GNU General Public License v3 (GPLv3)
Classifier: Operating System :: OS Independent
Requires-Python: >=3.5
Requires-Dist: doreah (>=1.4.5)
Requires-Dist: wand (>=0.5.4)
Requires-Dist: pillow (>=7.0.0)
Requires-Dist: suvorov (>=0.6.0)
Requires-Dist: oyaml
Requires-Dist: vermeer (>=0.1.0)
